swagger_client/__init__.py
swagger_client/api_client.py
swagger_client/configuration.py
swagger_client/rest.py
swagger_client/api/__init__.py
swagger_client/api/announcements_api.py
swagger_client/api/people_api.py
swagger_client/api/projects_api.py
swagger_client/api/publications_api.py
swagger_client/api/sshkeys_api.py
swagger_client/api/version_api.py
swagger_client/api/whoami_api.py
swagger_client/models/__init__.py
swagger_client/models/announcement_one.py
swagger_client/models/announcements.py
swagger_client/models/announcements_details.py
swagger_client/models/announcements_patch.py
swagger_client/models/announcements_post.py
swagger_client/models/api_options.py
swagger_client/models/api_options_details.py
swagger_client/models/api_options_one.py
swagger_client/models/api_options_one_api_endpoints.py
swagger_client/models/bastionkeys.py
swagger_client/models/bastionkeys_one.py
swagger_client/models/people.py
swagger_client/models/people_details.py
swagger_client/models/people_one.py
swagger_client/models/people_one_roles.py
swagger_client/models/people_patch.py
swagger_client/models/person.py
swagger_client/models/preferences.py
swagger_client/models/profile_people.py
swagger_client/models/profile_people_other_identities.py
swagger_client/models/profile_people_personal_pages.py
swagger_client/models/profile_projects.py
swagger_client/models/profile_projects_references.py
swagger_client/models/project.py
swagger_client/models/project_membership.py
swagger_client/models/projects.py
swagger_client/models/projects_details.py
swagger_client/models/projects_one.py
swagger_client/models/projects_patch.py
swagger_client/models/projects_personnel_patch.py
swagger_client/models/projects_post.py
swagger_client/models/projects_tags_patch.py
swagger_client/models/sshkey_pair.py
swagger_client/models/sshkey_pair_results.py
swagger_client/models/sshkeys.py
swagger_client/models/sshkeys_one.py
swagger_client/models/sshkeys_post.py
swagger_client/models/sshkeys_put.py
coreapi_swagger_client-1.0.1.dist-info/METADATA
coreapi_swagger_client-1.0.1.dist-info/WHEEL
coreapi_swagger_client-1.0.1.dist-info/top_level.txt
coreapi_swagger_client-1.0.1.dist-info/RECORD
